{
  "116318b63e8f96b0": {
    "c": "لا تغيير",
    "i": 1,
    "t": "p"
  },
  "14533b9d287048eb": [
    {
      "c": "نصائح للمطورين",
      "i": 1,
      "t": "h3"
    },
    {
      "c": [
        {
          "c": [
            {
              "c": "01",
              "i": 4,
              "t": "span"
            },
            {
              "c": [
                {
                  "c": [
                    "خطّط لتوسّع بنسبة ",
                    {
                      "i": 7,
                      "k": "_gt_n_7",
                      "v": "n"
                    },
                    "%."
                  ],
                  "i": 6,
                  "t": "strong"
                },
                " تتوسّع النصوص الإنجليزية في اللغتين الألمانية والفنلندية وغيرهما من اللغات الإلصاقية بنسبة ",
                {
                  "i": 8,
                  "k": "_gt_n_8",
                  "v": "n"
                },
                "-",
                {
                  "i": 9,
                  "k": "_gt_n_9",
                  "v": "n"
                },
                "% بشكل اعتيادي. صمّم واجهة المستخدم بحاويات مرنة قادرة على استيعاب هذا التوسّع."
              ],
              "i": 5,
              "t": "p"
            }
          ],
          "i": 3,
          "t": "div"
        },
        {
          "c": [
            {
              "c": "02",
              "i": 11,
              "t": "span"
            },
            {
              "c": [
                {
                  "c": "النصوص القصيرة تتوسّع أكثر.",
                  "i": 13,
                  "t": "strong"
                },
                " قد يصبح تسمية زر إنجليزية مؤلفة من ",
                {
                  "i": 14,
                  "k": "_gt_n_14",
                  "v": "n"
                },
                " حرفاً ",
                {
                  "i": 15,
                  "k": "_gt_n_15",
                  "v": "n"
                },
                " حرفاً في الألمانية. كلّما كان النص المصدر أقصر، كانت نسبة التوسّع أعلى."
              ],
              "i": 12,
              "t": "p"
            }
          ],
          "i": 10,
          "t": "div"
        },
        {
          "c": [
            {
              "c": "03",
              "i": 17,
              "t": "span"
            },
            {
              "c": [
                {
                  "c": "لغات CJK أكثر إيجازاً.",
                  "i": 19,
                  "t": "strong"
                },
                " تستخدم اللغتان الصينية واليابانية عدداً أقل من الأحرف، غير أن كل حرف يحمل معنىً أوسع. إلا أنها تستهلك بايتات أكثر لكل حرف في ترميز UTF-8."
              ],
              "i": 18,
              "t": "p"
            }
          ],
          "i": 16,
          "t": "div"
        },
        {
          "c": [
            {
              "c": "04",
              "i": 21,
              "t": "span"
            },
            {
              "c": [
                {
                  "c": "قِس البايتات لا الأحرف فحسب.",
                  "i": 23,
                  "t": "strong"
                },
                " قد يبدو النص العربي والصيني والياباني أقصر من حيث عدد الأحرف، لكنه قد يستهلك ",
                {
                  "i": 24,
                  "k": "_gt_n_24",
                  "v": "n"
                },
                "-",
                {
                  "i": 25,
                  "k": "_gt_n_25",
                  "v": "n"
                },
                "x بايتات أكثر في ترميز UTF-8. وهذا مهم لاعتبارات التخزين وعرض النطاق الترددي وتحديد أحجام أعمدة قواعد البيانات."
              ],
              "i": 22,
              "t": "p"
            }
          ],
          "i": 20,
          "t": "div"
        },
        {
          "c": [
            {
              "c": "05",
              "i": 27,
              "t": "span"
            },
            {
              "c": [
                {
                  "c": "تجنّب التخطيطات ذات العرض الثابت.",
                  "i": 29,
                  "t": "strong"
                },
                " استخدم CSS flexbox وgrid و",
                {
                  "c": "min-width",
                  "i": 30,
                  "t": "code"
                },
                " / ",
                {
                  "c": "max-width",
                  "i": 31,
                  "t": "code"
                },
                " بدلاً من عرض البكسل الثابت. اختبر التصميم مع أطول لغة مستهدفة، وليس الإنجليزية فحسب."
              ],
              "i": 28,
              "t": "p"
            }
          ],
          "i": 26,
          "t": "div"
        }
      ],
      "i": 2,
      "t": "div"
    }
  ],
  "3fdb1cae94856035": {
    "c": [
      "+",
      {
        "i": 2,
        "k": "_gt_value_2",
        "v": "v"
      },
      "% توسّع"
    ],
    "i": 1,
    "t": "p"
  },
  "5f5449f593ca0904": {
    "c": "النص المصدر (الإنجليزية):",
    "i": 1,
    "t": "p"
  },
  "6a3a84fec77cfa74": {
    "c": "تحليل طول اللغة",
    "i": 1,
    "t": "h1"
  },
  "6fdab6731b0efbef": {
    "c": [
      {
        "i": 2,
        "k": "_gt_value_2",
        "v": "v"
      },
      "% انكماش"
    ],
    "i": 1,
    "t": "p"
  },
  "7c02545d425ba44e": [
    {
      "c": "أعداد الأحرف في لمحة سريعة",
      "i": 1,
      "t": "h3"
    },
    {
      "c": "عدد الأحرف لكل ترجمة مع نسبة التمدد. يشير اللون الأحمر إلى تمدد ملحوظ، ويشير اللون الأخضر إلى تقلص.",
      "i": 2,
      "t": "p"
    }
  ],
  "85e1eff38e12945d": {
    "c": "اختر عبارة نموذجية لترى كيف تُترجم عبر اللغات المختلفة، مع عدد الأحرف والبايتات لكل منها.",
    "i": 1,
    "t": "p"
  },
  "aefea2b7d6c8c67f": [
    {
      "c": "النص",
      "i": 1,
      "t": "th"
    },
    {
      "c": "en",
      "i": 2,
      "t": "th"
    }
  ],
  "b5e4906043dd9ba3": {
    "c": "جرّبه بنفسك",
    "i": 1,
    "t": "h3"
  },
  "b996bb3e80916477": [
    {
      "c": "كيف يتغير النص عبر اللغات",
      "i": 1,
      "t": "h2"
    },
    {
      "c": [
        "عند ترجمة النص، يتغير طوله -- وأحياناً بشكل ملحوظ. تميل اللغة الألمانية إلى التمدد بنسبة ",
        {
          "i": 3,
          "k": "_gt_n_3",
          "v": "n"
        },
        "% أو أكثر، في حين كثيراً ما تنكمش اللغتان الصينية واليابانية. يُعدّ فهم هذه الأنماط أمراً ضرورياً لبناء واجهات مستخدم مدوَّلة."
      ],
      "i": 2,
      "t": "p"
    }
  ],
  "e330fcbc6db15c9f": [
    {
      "c": "مقارنة جنبًا إلى جنب",
      "i": 1,
      "t": "h3"
    },
    {
      "c": "اختر نصًا ومقياسًا لمعرفة كيف تبدو كل لغة بصريًا.",
      "i": 2,
      "t": "p"
    }
  ],
  "fb9975d3b387f335": [
    {
      "c": "متوسط نسبة التمدد",
      "i": 1,
      "t": "h3"
    },
    {
      "c": [
        "عدد الأحرف نسبةً إلى الإنجليزية عبر ",
        {
          "i": 3,
          "k": "_gt_n_3",
          "v": "n"
        },
        " نص نموذجي، من تسميات واجهة المستخدم القصيرة إلى الجمل الكاملة."
      ],
      "i": 2,
      "t": "p"
    }
  ]
}